lazy_nlp/__init__.py
lazy_nlp/nlp.py
lazy_nlp-1.0.3.dist-info/METADATA
lazy_nlp-1.0.3.dist-info/WHEEL
lazy_nlp-1.0.3.dist-info/top_level.txt
lazy_nlp-1.0.3.dist-info/RECORD
